gameboard/__init__.py
gameboard/grid.py
gameboard-1.0.9.1.dist-info/METADATA
gameboard-1.0.9.1.dist-info/WHEEL
gameboard-1.0.9.1.dist-info/top_level.txt
gameboard-1.0.9.1.dist-info/RECORD
