Metadata-Version: 2.1
Name: gameboard
Version: 1.0.9.1
Summary: A 3D grid creation library for simulation and games.
Home-page: https://github.com/Sprocketer/gameboard
Author: Alex
Author-email: sprocketerdev@gmail.com
Keywords: pypi,python
Classifier: Development Status :: 4 - Beta
Classifier: Intended Audience :: Developers
Classifier: Programming Language :: Python :: 3
Classifier: Operating System :: Unix
Classifier: Operating System :: MacOS :: MacOS X
Classifier: Operating System :: Microsoft :: Windows
